roll_cy/__init__.py
roll_cy/setup.py
roll_cy-1.0.91.dist-info/METADATA
roll_cy-1.0.91.dist-info/WHEEL
roll_cy-1.0.91.dist-info/top_level.txt
roll_cy-1.0.91.dist-info/RECORD
