Metadata-Version: 2.1
Name: roll_cy
Version: 1.0.91
Author-email: Aprilwill <wenfangshangguan@gmail.com>
Requires-Python: >=3.9
Requires-Dist: numpy
